reclip/__init__.py
reclip/__main__.py
reclip/client.py
reclip/server.py
reclip-1.0.2.dist-info/LICENSE
reclip-1.0.2.dist-info/METADATA
reclip-1.0.2.dist-info/WHEEL
reclip-1.0.2.dist-info/entry_points.txt
reclip-1.0.2.dist-info/top_level.txt
reclip-1.0.2.dist-info/RECORD
