Metadata-Version: 2.1
Name: reclip
Version: 1.0.2
Summary: a clipboard server
Home-page: https://github.com/laddge/reclip
Author: Laddge
Author-email: dev.laddge@gmail.com
License: MIT
Platform: UNKNOWN
License-File: LICENSE
